cal_lcheng-0.0.2.data/data/hellohi/rec.txt
lcheng_cal/cal1.py
lcheng_cal/src/__init__.py
lcheng_cal/src/cal2.py
lcheng_cal/src/cal3.py
cal_lcheng-0.0.2.dist-info/METADATA
cal_lcheng-0.0.2.dist-info/WHEEL
cal_lcheng-0.0.2.dist-info/top_level.txt
cal_lcheng-0.0.2.dist-info/RECORD
